aaf2/__init__.py
aaf2/ama.py
aaf2/audio.py
aaf2/auid.py
aaf2/cache.py
aaf2/cfb.py
aaf2/components.py
aaf2/content.py
aaf2/core.py
aaf2/dictionary.py
aaf2/essence.py
aaf2/exceptions.py
aaf2/file.py
aaf2/interpolation.py
aaf2/metadict.py
aaf2/misc.py
aaf2/mobid.py
aaf2/mobs.py
aaf2/mobslots.py
aaf2/mxf.py
aaf2/properties.py
aaf2/rational.py
aaf2/types.py
aaf2/utils.py
aaf2/video.py
aaf2/model/__init__.py
aaf2/model/classdefs.py
aaf2/model/datadefs.py
aaf2/model/typedefs.py
aaf2/model/ext/__init__.py
aaf2/model/ext/classdefs.py
aaf2/model/ext/typedefs.py
pyaaf2-1.7.0.dist-info/LICENSE
pyaaf2-1.7.0.dist-info/METADATA
pyaaf2-1.7.0.dist-info/WHEEL
pyaaf2-1.7.0.dist-info/top_level.txt
pyaaf2-1.7.0.dist-info/RECORD
