Metadata-Version: 2.1
Name: pyaaf2
Version: 1.7.0
Summary: A python module for reading and writing advanced authoring format files
Home-page: https://github.com/markreidvfx/pyaaf2
Author: Mark Reid
Author-email: mindmark@gmail.com
License: MIT
Project-URL: Source, https://github.com/markreidvfx/pyaaf2
Project-URL: Documentation, http://pyaaf.readthedocs.io
Project-URL: Issues, https://github.com/markreidvfx/pyaaf2/issues
Keywords: film tv editing editorial edit non-linear edl time
Platform: any
Classifier: Development Status :: 3 - Alpha
Classifier: Topic :: Multimedia :: Graphics
Classifier: Topic :: Multimedia :: Video
Classifier: Topic :: Multimedia :: Video :: Display
Classifier: Topic :: Multimedia :: Video :: Non-Linear Editor
Classifier: Topic :: Software Development :: Libraries :: Python Modules
Classifier: License :: OSI Approved :: MIT License
Classifier: Programming Language :: Python :: 2
Classifier: Programming Language :: Python :: 2.7
Classifier: Programming Language :: Python :: 3
Classifier: Programming Language :: Python :: 3.7
Classifier: Programming Language :: Python :: 3.8
Classifier: Programming Language :: Python :: 3.9
Classifier: Programming Language :: Python :: 3.10
Classifier: Operating System :: OS Independent
Classifier: Natural Language :: English
Requires-Python: >=2.7, !=3.0.*, !=3.1.*, !=3.2.*, !=3.3.*, !=3.4.*, !=3.5.*, !=3.6.*
License-File: LICENSE
